__init__.py
__main__.py
anonymizer.py
exceptions.py
segmenter.py
server.py
vault.py
extractors/__init__.py
extractors/azure_di.py
extractors/base.py
extractors/docling.py
extractors/llamaindex.py
extractors/mineru.py
extractors/registry.py
inkognito-0.1.0.dist-info/METADATA
inkognito-0.1.0.dist-info/WHEEL
inkognito-0.1.0.dist-info/entry_points.txt
inkognito-0.1.0.dist-info/licenses/LICENSE
inkognito-0.1.0.dist-info/RECORD
