Metadata-Version: 2.4
Name: inkognito
Version: 0.1.0
Summary: Privacy-first document processing FastMCP server with PII anonymization
Project-URL: Homepage, https://github.com/phren0logy/inkognito
Project-URL: Repository, https://github.com/phren0logy/inkognito
Project-URL: Issues, https://github.com/phren0logy/inkognito/issues
Project-URL: Documentation, https://github.com/phren0logy/inkognito#readme
Author-email: Andrew Nanton <git-nanton@stanford.edu>
License: MIT
License-File: LICENSE
Keywords: anonymization,document-processing,extraction,fastmcp,mcp,pdf,pii,privacy
Classifier: Development Status :: 4 - Beta
Classifier: Intended Audience :: Developers
Classifier: License :: OSI Approved :: MIT License
Classifier: Programming Language :: Python :: 3
Classifier: Programming Language :: Python :: 3.10
Classifier: Programming Language :: Python :: 3.11
Classifier: Programming Language :: Python :: 3.12
Classifier: Topic :: Security
Classifier: Topic :: Software Development :: Libraries :: Python Modules
Classifier: Topic :: Text Processing :: General
Requires-Python: <3.13,>=3.10
Requires-Dist: aiofiles>=23.0.0
Requires-Dist: docling>=2.25
Requires-Dist: faker>=20.0.0
Requires-Dist: fastmcp>=2.11.0
Requires-Dist: llm-guard>=0.3.0
Requires-Dist: ocrmac>=1.0.0
Requires-Dist: pip>=25.2
Requires-Dist: python-magic>=0.4.0
Requires-Dist: tiktoken>=0.5.0
Provides-Extra: all
Requires-Dist: azure-ai-documentintelligence>=1.0.0b1; extra == 'all'
Requires-Dist: docling>=1.0.0; extra == 'all'
Requires-Dist: llama-index>=0.9.0; extra == 'all'
Requires-Dist: llama-parse>=0.3.0; extra == 'all'
Requires-Dist: magic-pdf>=0.6.0; extra == 'all'
Provides-Extra: azure
Requires-Dist: azure-ai-documentintelligence>=1.0.0b1; extra == 'azure'
Provides-Extra: docling
Requires-Dist: docling>=1.0.0; extra == 'docling'
Provides-Extra: llamaindex
Requires-Dist: llama-index>=0.9.0; extra == 'llamaindex'
Requires-Dist: llama-parse>=0.3.0; extra == 'llamaindex'
Provides-Extra: mineru
Requires-Dist: magic-pdf>=0.6.0; extra == 'mineru'
